stickNAUTA/NautaSession.py
stickNAUTA/PortalNauta.py
stickNAUTA/__init__.py
stickNAUTA-2.0.2.dist-info/LICENSE
stickNAUTA-2.0.2.dist-info/METADATA
stickNAUTA-2.0.2.dist-info/WHEEL
stickNAUTA-2.0.2.dist-info/top_level.txt
stickNAUTA-2.0.2.dist-info/RECORD
