Metadata-Version: 2.1
Name: stickNAUTA
Version: 2.0.2
Summary: Simple managing interface for ETECSA Nauta.
Home-page: https://github.com/stickM4N/stickNAUTA
Download-URL: https://pypi.org/project/stickNAUTA
Author: stickM4N
Author-email: jcgalindo.jcgh@gmail.com
License: MIT
Keywords: python nauta etecsa
Classifier: Programming Language :: Python :: 3
Classifier: Programming Language :: Python :: 3.7
Classifier: Programming Language :: Python :: 3.8
Classifier: Programming Language :: Python :: 3.9
Classifier: Programming Language :: Python :: 3.10
Classifier: License :: OSI Approved :: MIT License
Classifier: Operating System :: OS Independent
Classifier: Topic :: Internet
Classifier: Topic :: Internet :: WWW/HTTP :: Session
Classifier: Topic :: Internet :: WWW/HTTP :: Site Management
Requires-Python: >=3.7
License-File: LICENSE
Requires-Dist: lxml
Requires-Dist: requests
